mimic_head/__init__.py
mimic_head/cli.py
mimic_head/live_portrait_pipeline_img.py
mimic_head/live_portrait_wrapper.py
mimic_head/mimic_head.py
mimic_head/config/__init__.py
mimic_head/config/argument_config.py
mimic_head/config/base_config.py
mimic_head/config/crop_config.py
mimic_head/config/inference_config.py
mimic_head/config/models.yaml
mimic_head/modules/__init__.py
mimic_head/modules/appearance_feature_extractor.py
mimic_head/modules/convnextv2.py
mimic_head/modules/dense_motion.py
mimic_head/modules/motion_extractor.py
mimic_head/modules/spade_generator.py
mimic_head/modules/stitching_retargeting_network.py
mimic_head/modules/util.py
mimic_head/modules/warping_network.py
mimic_head/utils/__init__.py
mimic_head/utils/camera.py
mimic_head/utils/crop.py
mimic_head/utils/cropper.py
mimic_head/utils/face_analysis_diy.py
mimic_head/utils/helper.py
mimic_head/utils/io.py
mimic_head/utils/landmark_runner.py
mimic_head/utils/retargeting_utils.py
mimic_head/utils/rprint.py
mimic_head/utils/timer.py
mimic_head/utils/video.py
mimic_head/utils/dependencies/__init__.py
mimic_head/utils/dependencies/insightface/__init__.py
mimic_head/utils/dependencies/insightface/app/__init__.py
mimic_head/utils/dependencies/insightface/app/common.py
mimic_head/utils/dependencies/insightface/app/face_analysis.py
mimic_head/utils/dependencies/insightface/data/__init__.py
mimic_head/utils/dependencies/insightface/data/image.py
mimic_head/utils/dependencies/insightface/data/pickle_object.py
mimic_head/utils/dependencies/insightface/data/rec_builder.py
mimic_head/utils/dependencies/insightface/model_zoo/__init__.py
mimic_head/utils/dependencies/insightface/model_zoo/arcface_onnx.py
mimic_head/utils/dependencies/insightface/model_zoo/attribute.py
mimic_head/utils/dependencies/insightface/model_zoo/inswapper.py
mimic_head/utils/dependencies/insightface/model_zoo/landmark.py
mimic_head/utils/dependencies/insightface/model_zoo/model_store.py
mimic_head-0.1.5.dist-info/LICENSE
mimic_head-0.1.5.dist-info/METADATA
mimic_head-0.1.5.dist-info/WHEEL
mimic_head-0.1.5.dist-info/entry_points.txt
mimic_head-0.1.5.dist-info/top_level.txt
mimic_head-0.1.5.dist-info/RECORD
