Metadata-Version: 2.1
Name: mimic_head
Version: 0.1.5
Summary: Unofficial One-click Version of LivePortrait, with Webcam Support
License-File: LICENSE
Requires-Dist: gradio
Requires-Dist: numpy
Requires-Dist: requests
Requires-Dist: opencv-python
Requires-Dist: onnxruntime
Requires-Dist: onnx
Requires-Dist: scikit-image
